pyscord_storage/__init__.py
pyscord_storage-2.0.4.dist-info/LICENSE
pyscord_storage-2.0.4.dist-info/METADATA
pyscord_storage-2.0.4.dist-info/WHEEL
pyscord_storage-2.0.4.dist-info/RECORD
