Metadata-Version: 2.1
Name: pyscord-storage
Version: 2.0.4
Summary: Free unlimited file hosting using the Discord server
Home-page: https://discord-storage.animemoe.us/
License: MIT
Keywords: discord,unlimited,storage,django
Author: Arter Tendean
Author-email: arter.tendean.07@gmail.com
Requires-Python: >=3.8,<4.0
Classifier: License :: OSI Approved :: MIT License
Classifier: Programming Language :: Python :: 3
Classifier: Programming Language :: Python :: 3.8
Classifier: Programming Language :: Python :: 3.9
Classifier: Programming Language :: Python :: 3.10
Classifier: Programming Language :: Python :: 3.11
Classifier: Programming Language :: Python :: 3.12
Requires-Dist: requests (>=2.28.2,<3.0.0)
Project-URL: Repository, https://github.com/animemoeus/pyscord-storage
